memory/__init__.py
memory/brain.py
memory/embeddings.py
memory/lmdb_vector_mapping.py
memory/vector_database.py
memory/resources/use_quantized.onnx
tests/__init__.py
tests/test_memory.py
chatmemorydb_lmdb_onnx-1.2.dist-info/LICENSE
chatmemorydb_lmdb_onnx-1.2.dist-info/METADATA
chatmemorydb_lmdb_onnx-1.2.dist-info/WHEEL
chatmemorydb_lmdb_onnx-1.2.dist-info/top_level.txt
chatmemorydb_lmdb_onnx-1.2.dist-info/RECORD
