Metadata-Version: 2.1
Name: chatmemorydb-lmdb-onnx
Version: 1.2
Author: Carlo Moro
Author-email: Carlo Moro <cnmoro@gmail.com>
Project-URL: Homepage, https://github.com/cnmoro/ChatMemory
Project-URL: Bug Tracker, https://github.com/cnmoro/ChatMemory/issues
Classifier: Programming Language :: Python :: 3
Classifier: License :: OSI Approved :: MIT License
Classifier: Operating System :: OS Independent
Requires-Python: >=3.7
License-File: LICENSE
Requires-Dist: numpy
Requires-Dist: lmdb
Requires-Dist: msgpack
Requires-Dist: pymongo
Requires-Dist: onnxruntime
Requires-Dist: onnxruntime-extensions
Requires-Dist: faiss-cpu
